loan_calculator/__init__.py
loan_calculator/interest_rate.py
loan_calculator/irr.py
loan_calculator/loan.py
loan_calculator/pmt.py
loan_calculator/projection.py
loan_calculator/utils.py
loan_calculator/grossup/__init__.py
loan_calculator/grossup/base.py
loan_calculator/grossup/functions.py
loan_calculator/grossup/iof.py
loan_calculator/grossup/iof_tax.py
loan_calculator/grossup/service_fee.py
loan_calculator/schedule/__init__.py
loan_calculator/schedule/base.py
loan_calculator/schedule/constant.py
loan_calculator/schedule/price.py
loan_calculator-1.2.2.dist-info/AUTHORS.rst
loan_calculator-1.2.2.dist-info/LICENSE
loan_calculator-1.2.2.dist-info/METADATA
loan_calculator-1.2.2.dist-info/WHEEL
loan_calculator-1.2.2.dist-info/top_level.txt
loan_calculator-1.2.2.dist-info/RECORD
